cmd/__init__.py
cmd/main.py
example/__init__.py
example/personnel/__init__.py
example/personnel/albert-einstein.json
example/personnel/claude-monet.json
example/personnel/homer-simpson.json
example/personnel/marie-curie.json
example/personnel/pablo-picasso.json
example/personnel/vincent-van-gogh.json
example/personnel/walter-white.json
jam/__init__.py
jam/base.py
jam/core.py
jam/version.py
jam/instrument/__init__.py
jam/instrument/base.py
jam/instrument/image.py
jam/instrument/text.py
jam/interface/__init__.py
jam/interface/base.py
jam/interface/openai.py
jam/interface/stability_ai.py
jam/interface/writesonic.py
jam/persistence/__init__.py
jam/persistence/base.py
jam/persistence/memory.py
jam/persistence/model.py
jam/persistence/mysql.py
jam/persistence/postgres.py
jam/persistence/sqlite.py
jam/personnel/__init__.py
jam/personnel/base.py
jam/personnel/personnel.py
jam/util/__init__.py
jam/util/generate.py
jam/util/prompt.py
jam/util/search.py
tests/__init__.py
tests/instrument/__init__.py
tests/instrument/test_base.py
tests/interface/__init__.py
tests/interface/test_base.py
tests/test_persistence/__init__.py
tests/test_persistence/test_base.py
jam_ai-0.2.1.dist-info/METADATA
jam_ai-0.2.1.dist-info/WHEEL
jam_ai-0.2.1.dist-info/licenses/LICENSE
jam_ai-0.2.1.dist-info/RECORD
