Metadata-Version: 2.1
Name: jam-ai
Version: 0.2.1
Summary: Engaging with Multiple AI Agents with Jam.
Project-URL: homepage, https://github.com/abhishtagatya/jam
Project-URL: documentation, https://github.com/abhishtagatya/jam
Project-URL: changelog, https://github.com/abhishtagatya/jam/blob/master/CHANGELOG.md
Author-email: Abhishta Gatya <abhishtagatya@yahoo.com>
License:                                  Apache License
License-File: LICENSE
Keywords: chat engine,collaboration,data science,machine learning,multi agent,openai
Classifier: Development Status :: 3 - Alpha
Classifier: Intended Audience :: Developers
Classifier: Intended Audience :: Education
Classifier: Intended Audience :: Information Technology
Classifier: Intended Audience :: Science/Research
Classifier: License :: OSI Approved :: Apache Software License
Classifier: Natural Language :: English
Classifier: Operating System :: OS Independent
Classifier: Programming Language :: Python :: 3.9
Classifier: Programming Language :: Python :: 3.10
Classifier: Programming Language :: Python :: 3.11
Classifier: Topic :: Adaptive Technologies
Classifier: Topic :: Communications :: Chat
Classifier: Topic :: Scientific/Engineering :: Artificial Intelligence
Classifier: Topic :: Software Development :: Libraries
Classifier: Topic :: Software Development :: Libraries :: Python Modules
Requires-Python: >=3.9
Requires-Dist: openai
Requires-Dist: pillow
Requires-Dist: requests
Requires-Dist: rich
Requires-Dist: sqlalchemy
